spectralnet/__init__.py
spectralnet/_cluster.py
spectralnet/_metrics.py
spectralnet/_reduction.py
spectralnet/_utils.py
spectralnet/_losses/__init__.py
spectralnet/_losses/_siamese_loss.py
spectralnet/_losses/_spectralnet_loss.py
spectralnet/_models/__init__.py
spectralnet/_models/_ae_model.py
spectralnet/_models/_siamesenet_model.py
spectralnet/_models/_spectralnet_model.py
spectralnet/_trainers/__init__.py
spectralnet/_trainers/_ae_trainer.py
spectralnet/_trainers/_siamesenet_trainer.py
spectralnet/_trainers/_spectralnet_trainer.py
spectralnet/_trainers/_trainer.py
tests/__init__.py
spectralnet-0.1.2.dist-info/LICENSE.md
spectralnet-0.1.2.dist-info/METADATA
spectralnet-0.1.2.dist-info/WHEEL
spectralnet-0.1.2.dist-info/top_level.txt
spectralnet-0.1.2.dist-info/RECORD
