Metadata-Version: 2.1
Name: spectralnet
Version: 0.1.2
Summary: Spectral Clustering Using Deep Neural Networks
Home-page: https://github.com/shaham-lab/SpectralNet.git
Author: Amitai
Project-URL: Bug Tracker, https://github.com/shaham-lab/SpectralNet/issues
Classifier: Programming Language :: Python :: 3
Classifier: License :: OSI Approved :: MIT License
Classifier: Operating System :: OS Independent
Requires-Python: >=3.11
License-File: LICENSE.md
Requires-Dist: setuptools
Requires-Dist: wheel
Requires-Dist: torch >=2.0.0
Requires-Dist: torchvision >=0.15.1
Requires-Dist: h5py >=3.8.0
Requires-Dist: numpy >=1.24
Requires-Dist: annoy >=1.17.1
Requires-Dist: scipy >=1.10.1
Requires-Dist: munkres
Requires-Dist: matplotlib
Requires-Dist: scikit-learn >=1.2.2
